LICENSE
README.md
pyproject.toml
setup.cfg
setup.py
spych/__init__.py
spych/core.py
spych/utils.py
spych/wake.py
spych.egg-info/PKG-INFO
spych.egg-info/SOURCES.txt
spych.egg-info/dependency_links.txt
spych.egg-info/requires.txt
spych.egg-info/top_level.txt