Metadata-Version: 2.1
Name: spych
Version: 0.0.5
Summary: Python wrapper for the deepspeech library
Home-page: https://github.com/connor-makowski/spych
Download-URL: https://github.com/connor-makowski/spych/dist/spych-0.0.5.tar.gz
Author: Connor Makowski
Author-email: connor.m.makowski@gmail.com
License: MIT
Keywords: function,voice,machine,learning
Classifier: Development Status :: 3 - Alpha
Classifier: Intended Audience :: Developers
Classifier: Topic :: Software Development :: Build Tools
Classifier: License :: OSI Approved :: MIT License
Classifier: Programming Language :: Python :: 3
License-File: LICENSE
